Algoritmosnumericos/__init__.py
Algoritmosnumericos-0.3.0.dist-info/LICENCE.txt
Algoritmosnumericos-0.3.0.dist-info/METADATA
Algoritmosnumericos-0.3.0.dist-info/WHEEL
Algoritmosnumericos-0.3.0.dist-info/top_level.txt
Algoritmosnumericos-0.3.0.dist-info/RECORD
