Metadata-Version: 2.1
Name: Algoritmosnumericos
Version: 0.3.0
Summary: maths algorithms and util funtion for plot numerical methods
Home-page: https://github.com/Ratabart666
Author: Thomas Gomez
Author-email: t.gomezs2@uniandes.edu.co
License: MIT
Keywords: numerical methods
Classifier: Development Status :: 5 - Production/Stable
Classifier: Intended Audience :: Education
Classifier: Operating System :: Microsoft :: Windows :: Windows 10
Classifier: License :: OSI Approved :: MIT License
Classifier: Programming Language :: Python :: 3
License-File: LICENCE.txt
Requires-Dist: numpy
Requires-Dist: scipy
Requires-Dist: statistic
Requires-Dist: prettytable
Requires-Dist: matplotlib
